mcp_airflow_api/__init__.py
mcp_airflow_api/airflow_api.py
mcp_airflow_api/functions.py
mcp_airflow_api/prompt_template.md
mcp_airflow_api-2025.8.12.18.12.35.dist-info/licenses/LICENSE
mcp_airflow_api-2025.8.12.18.12.35.dist-info/METADATA
mcp_airflow_api-2025.8.12.18.12.35.dist-info/WHEEL
mcp_airflow_api-2025.8.12.18.12.35.dist-info/entry_points.txt
mcp_airflow_api-2025.8.12.18.12.35.dist-info/top_level.txt
mcp_airflow_api-2025.8.12.18.12.35.dist-info/RECORD
