Metadata-Version: 2.4
Name: mcp-airflow-api
Version: 2025.8.12.18.12.35
Summary: Model Context Protocol (MCP) server for Apache Airflow API integration. Provides comprehensive tools for managing Airflow clusters including service operations, configuration management, status monitoring, and request tracking.
Requires-Python: >=3.11
License-File: LICENSE
Requires-Dist: fastapi>=0.116.1
Requires-Dist: requests>=2.32.4
Requires-Dist: uvicorn>=0.35.0
Requires-Dist: mcp>=1.12.3
Dynamic: license-file
